p12-3.12.0.dev1.dist-info/METADATA
p12-3.12.0.dev1.dist-info/WHEEL
p12-3.12.0.dev1.dist-info/entry_points.txt
p12-3.12.0.dev1.dist-info/licenses/LICENSE
p12/__init__.py
p12/app.py
p12/twelve/__init__.py
p12-3.12.0.dev1.dist-info/RECORD
