Metadata-Version: 2.1
Name: p12
Version: 3.12.0.dev1
Summary: Stuff for Python 3.12.0
Author-Email: "D. Alex Graham" <alex@aode.space>
License: MIT
Requires-Python: >=3.12
Requires-Dist: typer>=0.12.5
Requires-Dist: version3900==3.9.0a0
